Workbook
Name BE_Total: #REF!
Name BE_Variable: #REF!
Name Suvartota_pašarams: #REF!
Name Table_total: #REF!
Name Revenue_increments: #REF!
Name Table_Variable: #REF!
Name Suvartota_sėklai: #REF!
Name Derlingumas: #REF!
Name Fixed_expenses: #REF!
Name Atsargos_t: #REF!
Name korekcijos_faktor: #REF!
Name Atsargos_t: #REF!
Name Pirkta_produkcija: #REF!
Name BE_Revenue: #REF!
Name Revenue_increments: #REF!
Name Contribution_margin: #REF!
Name Table_Revenue: #REF!
Name Parduota_natūra: #REF!
Name BE_Fixed: #REF!
Name Pardavimai_Lt: #REF!
Name ats: #REF!
Name Atsargos_t: #REF!
Name ats: #REF!
Name Atsargos_t: #REF!
Name Pardavimai_užskaitoma: #REF!
Name Table_Fixed: #REF!
Name Revenue_increments: #REF!
Name Derlius: #REF!
Name Išlaidos_Lt: #REF!
Name ats: #REF!
Name Plotas: #REF!
Name Kainos: #REF!
Name ats: #REF!
Name Revenue_increments: #REF!
Name korekcijos_faktor2: #REF!
Name Išlaikymo_nuostoliai: #REF!

Sheet Invesment
D2: 1 scenario | G2: 2 scenario
B3: Project value and funding sources, EUR | C3: EUR, without VAT | F3: EUR, without VAT
C4: Total | D4: 2018 | E4: 2019 | F4: Total | G4: 2018 | H4: 2019
B5: Investments in fixed assets - equipment | C5: 1528273.2 | D5: =C5*0.4 -> 611309.28 | E5: =C5*0.6 -> 916963.92 | F5: 0 | G5: =F5*0.4 -> 0 | H5: =F5*0.6 -> 0
B6: Investments in fixed assets - buildings | C6: 3000000 | E6: =C6 -> 3000000
B7: Salary of the project implementation team | C7: 140000 | D7: =C7*0.4 -> 56000 | E7: =C7*0.6 -> 84000 | F7: 0 | G7: =F7*0.4 -> 0 | H7: =F7*0.6 -> 0
B8: Purchase of services | C8: 750000 | D8: =C8*0.5 -> 375000 | E8: =D8 -> 375000 | F8: 8000000 | G8: =F8*0.5 -> 4000000 | H8: =G8 -> 4000000
B9: Total value of the project | C9: =SUM(C5:C8) -> 5418273.2 | D9: =SUM(D5:D8) -> 1042309.3 | E9: =SUM(E5:E8) -> 4375963.9 | F9: =SUM(F5:F8) -> 8000000 | G9: =SUM(G5:G8) -> 4000000 | H9: =SUM(H5:H8) -> 4000000
B11: Private investment (third party) | C11: 1200000 | D11: =C11-E11 -> 500000 | E11: 700000 | F11: 0 | G11: 0 | H11: 0
B12: Own funds | C12: =C9-C11-C13 -> 2718273.2 | D12: =D9-D11-D13 -> 92309.28 | E12: =E9-E11-E13 -> 2625963.9 | F12: =F9-F11-F13 -> 8000000 | G12: =G9-G11-G13 -> 4000000 | H12: =H9-H11-H13 -> 4000000
B13: Financing of credit institutions | C13: 1500000 | D13: =C13*0.3 -> 450000 | E13: =C13-D13 -> 1050000 | F13: 0 | G13: =F13*0.4 -> 0 | H13: =F13*0.6 -> 0
B14: Project funding sources, total | C14: =SUM(C11:C13) -> 5418273.2 | D14: =SUM(D11:D13) -> 1042309.3 | E14: =SUM(E11:E13) -> 4375963.9 | F14: =SUM(F11:F13) -> 8000000 | G14: =SUM(G11:G13) -> 4000000 | H14: =SUM(H11:H13) -> 4000000
C15: =C14-C9 -> 0 | D15: =D14-D9 -> 0 | E15: =E14-E9 -> 0 | F15: =F14-F9 -> 0 | G15: =G14-G9 -> 0 | H15: =H14-H9 -> 0
B17: Loan terms
B18: Private investment
B19: Duration - 5 years, interest rate - 5 percent.
B20: Refund - at expiration.
B22: Bank loan
B23: Duration - 3 years, interest rate - 3 percent.
B24: Repayment - a yearly loan balance of EUR 500,000 is repaid..

Sheet Income Statement
C2: Statement of profit or loss(Income Statement), EUR
C3: Articles | D3: 2016 | E3: 2017
B5: I. | C5: SALES REVENUE | D5: 2714177.5 | E5: 4414253.6 | G5: Growth | H5: =(E5-D5)/D5 -> 0.62636883
B6: II. | C6: COST OF SALES | D6: 998289.54 | E6: 1121942.5
C7: Depreciation and amortization | D7: 0 | E7: 0 | K7: average salary each month for 24 month*
C8: Materials (raw materials) | D8: 992551.55 | E8: 1076892.7 | F8: =E8*1.24 -> 1335346.9
C9: Wage | E9: =E8/E5 -> 0.24395804
C10: Rental of industrial premises
C11: Others | D11: 5737.9852 | E11: 45049.815
B12: III. | C12: GROSS PROFIT (LOSS) | D12: =SUM(D5-D6) -> 1715887.9 | E12: =SUM(E5-E6) -> 3292311.2
B13: IV. | C13: OPERATING COSTS | D13: =SUM(D14,D19) -> 1367820.1 | E13: =SUM(E14,E19) -> 2932586.3 | M13: =(60-9)/23 -> 2.2173913
B14: IV.1 | C14: For sale | D14: 726794.2 | E14: =sum(E17:E18) -> 534191.72 | F14: ?
C15: Depreciation and amortization | M15: Employee | N15: How many months worked
C16: Wage | L16: 201601 | M16: 9 | N16: =M16*1 -> 9 | O16: 12 | P16: 201701 | Q16: =sum(M16:M27) -> 31.173913
C17: Marketing | D17: 352544 | E17: 523344 | L17: 201602 | M17: =$M$13*1 -> 2.2173913 | N17: =M17*11/12 -> 2.0326087 | O17: 11
C18: Others | D18: 374250.2 | E18: 10847.718 | L18: 201603 | M18: =$M$13*1 -> 2.2173913 | N18: =M18*10/12 -> 1.8478261 | O18: 10
B19: IV.2 | C19: General and administrative | D19: =SUM(D20:D23) -> 641025.87 | E19: =SUM(E20:E23) -> 2398394.6 | L19: 201604 | M19: =$M$13*1 -> 2.2173913 | N19: =M19*O19/12 -> 1.6630435 | O19: 9
C20: Depreciation and amortization | D20: 140511.18 | E20: 203121.81 | L20: 201605 | N20: =M19*O20/12 -> 1.4782609 | O20: 8
C21: Wage | D21: 499966.69 | E21: 1368507 | G21: Average Salary( assumption) | H21: =(D21+E21)/24 -> 77853.071 | I21: =H21/34.5 -> 2256.6108 | L21: 201606 | M21: =$M$13*1 -> 2.2173913 | N21: =M21*O21/12 -> 1.2934783 | O21: 7
C22: Rent of premises | G22: Inflation Rate (ECB policy) | H22: 0.02 | L22: 201607 | M22: =$M$13*1 -> 2.2173913 | N22: =M22*O22/12 -> 1.1086957 | O22: 6
C23: Others | D23: 548 | E23: 826765.77 | G23: Discount Rate | H23: 0.1 | I23: ITF | L23: 201608 | M23: =$M$13*1 -> 2.2173913 | N23: =M23*O23/12 -> 0.92391304 | O23: 5
B24: V. | C24: OPERATING PROFIT | D24: =SUM(D12-D13) -> 348067.87 | E24: =SUM(E12-E13) -> 359724.86 | G24: Evalutation Period in years | H24: 5 | I24: recommended to use less years | L24: 201609 | M24: =$M$13*1 -> 2.2173913 | N24: =M24*O24/12 -> 0.73913043 | O24: 4
B25: VI. | C25: ANOTHER ACTIVITY | D25: =SUM(D26-D27) -> 4344.3003 | E25: =SUM(E26-E27) -> 89548.193 | L25: 201610 | M25: =$M$13*1 -> 2.2173913 | N25: =M25*O25/12 -> 0.55434783 | O25: 3
B26: VI.1. | C26: Income | D26: =15000/3.4528 -> 4344.3003 | E26: =309192/3.4528 -> 89548.193 | L26: 201611 | M26: =$M$13*1 -> 2.2173913 | N26: =M26*O26/12 -> 0.36956522 | O26: 2
B27: VI.2. | C27: Costs | D27: 0 | E27: 0 | L27: 201612 | M27: =$M$13*1 -> 2.2173913 | N27: =M27*O27/12 -> 0.18478261 | O27: 1
B28: VII. | C28: FINANCING AND INVESTING ACTIVITIES | D28: =SUM(D29-D30) -> -9701.1121 | E28: =SUM(E29-E30) -> -21799.12 | N28: =SUM(N16:N27) -> 21.195652 | Q28: =Q16+sum(N17:N27) -> 43.369565
B29: VII.1. | C29: Income | D29: =11633/3.4528 -> 3369.1497 | E29: =9444/3.4528 -> 2735.1715 | N29: =D21/N28 -> 23588.172 | Q29: =E21/Q28 -> 31554.548
B30: VII.2. | C30: Costs | D30: =45129/3.4528 -> 13070.262 | E30: =84712/3.4528 -> 24534.291
B31: X. | C31: LOSSES
B32: XI. | C32: PROFIT (LOSS) BEFORE TAX | D32: 342711.06 | E32: 427473.93
B33: XII. | C33: INCOME TAX | D33: 54291.01 | E33: 62089.608
B34: XIII. | C34: NET PROFIT (LOSS) | D34: 288420.05 | E34: 365384.33
D36: 0 | E36: 0

Sheet Balance sheet
B3: Articles | C3: Actual
C4: 2016 | D4: 2017
B5: FIXED ASSETS | C5: 1321427 | D5: 1249622.9
B6: INTANGIBLE ASSETS | C6: 1345.5746 | D6: 1572.6367
B7: Patents and licenses | C7: 0 | D7: 0
B8: software | C8: 0 | D8: 0
B9: Other current assets | C9: 1345.5746 | D9: 1572.6367
B10: TANGIBLE ASSETS | C10: 1184828.8 | D10: 1098770
B11: Land | C11: 0 | D11: 0
B12: Buildings and structures | C12: 728233.61 | D12: 585547.38
B13: Machinery and equipment | C13: 323297.03 | D13: 222930.95
B14: Vehicles | C14: 130161.32 | D14: 249225.56
B15: Other equipment, tools and installations | C15: 3136.8744 | D15: 41066.091
B16: Construction work in progress | C16: 0 | D16: 0
... B45: Profit (loss) for the previous year | C45: 164753.03 | D45: 453173.08
C46: 0 | D46: 0
B47: GRANTS AND SUBSIDIES | C47: 0 | D47: 0
C48: 0 | D48: 0
B49: PAYMENT SUMS AND LIABILITIES | C49: 1281872.7 | D49: 947969.61
B50: AMOUNTS PAYABLE AFTER ONE YEAR AND NON-CURRENT LIABILITIES | C50: 523639.37 | D50: 105177.83
B51: Financial debts | C51: 394759.04 | D51: 0
B52: Other debts | C52: 75011.006 | D52: 105177.83
B53: Other | C53: 53869.323 | D53: 0
B54: AMOUNTS PAYABLE WITHIN ONE YEAR AND CURRENT LIABILITIES | C54: 758233.32 | D54: 842791.78
B55: Current part of long - term debt | C55: 42556.476 | D55: 54738.473
B56: Financial debts | C56: 89784.523 | D56: 0
B57: Debts to suppliers | C57: 267060.07 | D57: 391348.47
B58: Other | C58: 358832.25 | D58: 396704.83
B59: TOTAL EQUITY AND LIABILITIES: | C59: 1738231.6 | D59: 1769712.8

Sheet Cash flows
B2: Articles | C2: Actual
C3: 2016 | D3: 2017
B4: Cash inflow (including VAT): | C4: =SUM(C5:C6) -> 3418804.8 | D4: =SUM(D5:D6) -> 5477916.7
B5: From customers | C5: ='Income Statement'!D5*1.21 -> 3284154.8 | D5: ='Income Statement'!E5*1.21 -> 5341246.9
B6: Others | C6: 134650 | D6: =C6*1.015 -> 136669.75
B7: Cash benefits: | C7: =SUM(C8:C11) -> -2865267.3 | D7: =SUM(D8:D11) -> -4917989.9
B8: Money paid to suppliers | C8: -2232103.6 | D8: -3598006.6
B9: For wages | C9: -499966.69 | D9: -1368507
B10: Fees paid | C10: -238 | D10: 70322.795
B11: Other benefits | C11: -132959 | D11: -21799.12
B12: Net cash flows from manufacturing activities | C12: =C4+C7 -> 553537.42 | D12: =D4+D7 -> 559926.73
B14: Acquisition of fixed assets | C14: -351467.22 | D14: -243493.98
B15: Transfer of fixed assets | C15: 0 | D15: 291013.38
B16: Other cash flows from investing activities (listed) | C16: -131719.18 | D16: -14027.746
B17: Net cash flows from investing activities | C17: =SUM(C14:C16) -> -483186.4 | D17: =SUM(D14:D16) -> 33491.659
B19: Shareholders' contributions | C19: 0 | D19: 0
B20: Dividends are paid
B21: Obtaining loans | C21: 53869.323 | D21: 0
B22: Repayment of loans | C22: -56671.687 | D22: -576913.23
B23: Interest paid | C23: -11716.867 | D23: -13756.372
B24: Other cash flows from financing activities | C24: 2253.5334 | D24: -7818.0028
B25: Net cash flows from financing activities | C25: =SUM(C19:C24) -> -12265.697 | D25: =SUM(D19:D24) -> -598487.6
B27: Cash flow | C27: =SUM(C25,C17,C12) -> 58085.322 | D27: =SUM(D25,D17,D12) -> -5069.2192
B28: Amount of money at the beginning of the year | C28: 127541.71 | D28: =C29 -> 185627.03
B29: Amount of money at the end of the year | C29: =C28+C27 -> 185627.03 | D29: =D28+D27 -> 180557.81
B31: Check | C31: 5.8207661e-10 | D31: -2.3283064e-10
C32: =C29-'Balance sheet'!C31 -> 5.2386895e-10 | D32: =D29-'Balance sheet'!D31 -> -2.3283064e-10

Sheet Task
A1: Average Salary( assumption) | B1: 32185
A2: Inflation Rate (ECB policy) | B2: 0.02 | M2: ='Income Statement'!E9 -> 0.24395804
A3: Discount Rate | B3: 0.1 | G3: inflows of the project | M3: material | N3: cost of investment
A4: Evalutation Period in years | B4: 5 | E4: Year | F4: Revenue | G4: Increment | H4: Marketing | I4: Salary | J4: material | K4: Initial Investment | L4: Financing Payments | M4: Cumilative | N4: Net Cash Flow
A5: Marketing Cost Assumption | B5: 0.05 | E5: 43465 | F5: =B7 -> 4414254 | G5: =$F5-$B$7 -> 0 | H5: =$G5*0.05 -> 0 | I5: =$B$12 -> 321850 | J5: 0 | K5: =Invesment!D11*0.05+Invesment!D13*0.03+Invesment!D13 -> 488500 | L5: =$B$16+Invesment!C13*B15+60000 -> 605000 | M5: =N5 -> -810350 | N5: =$G5-$H5-$I5-$J5-$K5 -> -810350
A6: Scenario 1: | E6: 43830 | F6: =B7 -> 4414254 | G6: =$F6-$B$7 -> 0 | H6: =$G6*0.05 -> 0 | I6: =$B$12 -> 321850 | J6: 0 | K6: =Invesment!E9 -> 4375963.9 | L6: =$B$16+1000000*B15+60000 -> 590000 | M6: =$N5+$N6 -> -5508163.9 | N6: =$G6-$H6-$I6-$J6-$K6 -> -4697813.9
A7: Initial Revenue | B7: 4414254 | E7: 44196 | F7: =F6*1.5 -> 6621381 | G7: =$F7-$B$7 -> 2207127 | H7: =$G7*0.05 -> 110356.35 | I7: =$B$12 -> 321850 | J7: =G7*$M$2 -> 538446.38 | L7: =B16+B16*B15+60000 -> 575000 | M7: =$N6+$N7 -> -3461339.6 | N7: =$G7-$H7-$I7-$J7-$K7 -> 1236474.3
A8: After project: | B8: =B7*1.5 -> 6621381 | E8: 44561 | F8: =$F7*1.1 -> 7283519.1 | G8: =$F8-$B$7 -> 2869265.1 | H8: =$G8*0.05 -> 143463.26 | I8: =$B$12 -> 321850 | J8: =G8*$M$2 -> 699980.29 | L8: =+60000 -> 60000 | M8: =$N7+$N8 -> 2940445.8 | N8: =$G8-$H8-$I8-$J8-$K8 -> 1703971.6
A9: Annual Growth | B9: 0.1 | E9: 44926 | F9: =$F8*1.1 -> 8011871 | G9: =$F9-$B$7 -> 3597617 | H9: =$G9*0.05 -> 179880.85 | I9: =$B$12 -> 321850 | J9: =G9*$M$2 -> 877667.59 | L9: =C16+60000 -> 1260000 | M9: =$N8+$N9 -> 3922190.1 | N9: =$G9-$H9-$I9-$J9-$K9 -> 2218218.6
A10: Additional Costs
A11: Employess | B11: 10
A12: Wage per year | B12: =B1*B11 -> 321850
B14: Bank | C14: Private Investment
A15: Loan Interest | B15: 0.03 | C15: 0.05
A16: Loan Principal | B16: 500000 | C16: 1200000
A17: Scenario 2 | B17: Year 1 | C17: Year 2 | D17: Year 3
A18: Investment | B18: 4000000 | C18: 4000000
A19: Revenue growth | B19: 0.3 | C19: 0.3 | D19: 0.15
A20: Revenue projection | B20: =B7*1.3 -> 5738530.2 | C20: =B20*1.3 -> 7460089.3 | D20: =C20*1.15 -> 8579102.6
A21: Cost
A22: Employes | B22: =10*B1*2 -> 643700
A23: Marketing | D23: 1000000
E25: Year | F25: Revenue | G25: Increment | H25: Marketing | I25: Salary | J25: material | K25: Initial Investment | L25: Financing Payment | M25: Cumilative | N25: Net Cash Flow
E26: 43465 | F26: =B18*1.3 -> 5200000 | G26: =$F26-$B$18 -> 1200000 | H26: =0 -> 0 | I26: =$B$12 -> 321850 | J26: 0 | K26: =B18 -> 4000000 | L26: 0 | M26: =N26 -> -3121850 | N26: =$G26-$H26-$I26-$J26-$K26 -> -3121850
A27: Financial metrics | B27: Scenario 1 | C27: Scenario 2 | E27: 43830 | F27: =F26*1.3 -> 6760000 | G27: =$F27-$B$18 -> 2760000 | H27: =0 -> 0 | I27: =$B$12 -> 321850 | J27: 0 | K27: =C18 -> 4000000 | L27: 0 | M27: =$N26+$N27 -> -4683700 | N27: =$G27-$H27-$I27-$J27-$K27 -> -1561850
A28: NPV | B28: {=NPV(10%,N7:N10)+N5+N6} -> -1309275 | C28: {=NPV(10%,N28:N30)+N26+N27} -> 4261785.7 | E28: 44196 | F28: =$F27*1.15 -> 7774000 | G28: =$F28-$B$18 -> 3774000 | H28: =$D$23 -> 1000000 | I28: =$B$12 -> 321850 | J28: 0 | L28: 0 | M28: =$N27+$N28 -> 890300 | N28: =$G28-$H28-$I28-$J28-$K28 -> 2452150
A29: IRR | B29: =IRR(N5:N10) -> -0.027573121 | C29: =IRR(N26:N30) -> 0.35346293 | E29: 44561 | F29: =$F28*1.15 -> 8940100 | G29: =$F29-$B$18 -> 4940100 | H29: =$D$23 -> 1000000 | I29: =$B$12 -> 321850 | J29: 0 | L29: 0 | M29: =$N28+$N29 -> 6070400 | N29: =$G29-$H29-$I29-$J29-$K29 -> 3618250
A30: Payback Period | B30: 3 years | C30: 3 years | E30: 44926 | F30: =$F29*1.15 -> 10281115 | G30: =$F30-$B$18 -> 6281115 | H30: =$D$23 -> 1000000 | I30: =$B$12 -> 321850 | J30: 0 | L30: 0 | M30: =$N29+$N30 -> 8577515 | N30: =$G30-$H30-$I30-$J30-$K30 -> 4959265
A31: ROI | B31: =SUM(N5:N10)/SUM(K5:K6)*100 -> -7.184749 | C31: =SUM(N26:N30)/SUM(K26:K27)*100 -> 79.324562
A32: Opportuinty Cost | B32: =C28 -> 4261785.7 | C32: =B28 -> -1309275
A68: Conclusion
A70: Scenario 1 generates negative NPV and IRR below the discount rate, indicating that the factory expansion project is not financially viable under current assumptions.
A72: Scenario 2 generates positive NPV (€4.26M) and IRR of 35%, significantly exceeding the 10% discount rate.
A74: Scenario 2 — the digital product and marketing strategy — is the financially preferable investment option.
